api/__init__.py
api/datasets.py
api/timeseries.py
pythonONSWrapper-0.0.1.dist-info/LICENSE
pythonONSWrapper-0.0.1.dist-info/METADATA
pythonONSWrapper-0.0.1.dist-info/WHEEL
pythonONSWrapper-0.0.1.dist-info/top_level.txt
pythonONSWrapper-0.0.1.dist-info/RECORD
